Adafruit_MAX31855-1.6.1.dist-info/metadata.json
Adafruit_MAX31855-1.6.1.dist-info/METADATA
Adafruit_MAX31855-1.6.1.dist-info/RECORD
Adafruit_MAX31855-1.6.1.dist-info/WHEEL
Adafruit_MAX31855-1.6.1.dist-info/DESCRIPTION.rst
Adafruit_MAX31855-1.6.1.dist-info/dependency_links.txt
Adafruit_MAX31855-1.6.1.dist-info/top_level.txt
Adafruit_MAX31855/__init__.py
Adafruit_MAX31855/MAX31855.py
